pyolex/__init__.py
pyolex/enumerations.py
pyolex/olex.py
pyolex/utilities.py
pyolex-0.0.1.dist-info/METADATA
pyolex-0.0.1.dist-info/WHEEL
pyolex-0.0.1.dist-info/licenses/LICENSE.md
pyolex-0.0.1.dist-info/RECORD
