Metadata-Version: 2.3
Name: pyolex
Version: 0.0.1
Summary: A python library for reading and writing Olex plotlayer ('Ruter') files
Project-URL: Homepage, https://github.com/joakimsk/pyolex
Project-URL: Issues, https://github.com/joakimsk/pyolex/issues
Author-email: Joakim Skjefstad <skjefstad.joakim@gmail.com>
License-File: LICENSE.md
Classifier: License :: OSI Approved :: GNU General Public License v3 (GPLv3)
Classifier: Operating System :: OS Independent
Classifier: Programming Language :: Python :: 3
Classifier: Topic :: Software Development :: Libraries :: Python Modules
Requires-Python: >=3.8
Provides-Extra: dev
Requires-Dist: check-manifest; extra == 'dev'
Requires-Dist: pytest>=3.7; extra == 'dev'
Requires-Dist: twine; extra == 'dev'
